README.md
setup.py
kubeluigi/__init__.py
kubeluigi/k8s.py
kubeluigi.egg-info/PKG-INFO
kubeluigi.egg-info/SOURCES.txt
kubeluigi.egg-info/dependency_links.txt
kubeluigi.egg-info/requires.txt
kubeluigi.egg-info/top_level.txt
test/__init__.py
test/kubernetes_helpers_test.py