Metadata-Version: 2.1
Name: kubeluigi
Version: 1.0.2
Summary: Luigi contribution to run Tasks as Kubernetes Jobs
Home-page: https://github.com/optimizely/kubeluigi
Author: Optimizely Datascience
Author-email: david.przybilla@optimizely.com
License: Apache License 2.0
Keywords: Kubeluigi Kubernetes luigi pipelines pipeline kubetask
Platform: UNKNOWN
Classifier: Development Status :: 4 - Beta
Classifier: Programming Language :: Python :: 3.7
Classifier: Programming Language :: Python :: 3.8
Classifier: Programming Language :: Python
Classifier: Intended Audience :: Developers
Classifier: License :: OSI Approved :: Apache Software License
Classifier: Topic :: Software Development
Classifier: Environment :: Plugins
